polystar/peaks.py
polystar/plot.py
polystar/__init__.py
polystar/_polystar.cpython-39-darwin.so
polystar/vis.py
polystar/COPYING
polystar/bound.py
polystar-0.4.5.dist-info/RECORD
polystar-0.4.5.dist-info/WHEEL
polystar-0.4.5.dist-info/COPYING
polystar-0.4.5.dist-info/top_level.txt
polystar-0.4.5.dist-info/METADATA
