Metadata-Version: 2.1
Name: polystar
Version: 0.4.5
Summary: Polygon and polyhedron operations
Author-email: Gregory Tucker <gregory.tucker@ess.eu>
Maintainer-email: Gregory Tucker <gregory.tucker@ess.eu>
Project-URL: Homepage, https://github.com/g5t/polystar
Project-URL: Repository, https://github.com/g5t/polystar.git
Project-URL: Issues, https://github.com/g5t/polystar/issues
Classifier: Development Status :: 2 - Pre-Alpha
Classifier: Intended Audience :: Science/Research
Classifier: License :: OSI Approved :: GNU Affero General Public License v3 or later (AGPLv3+)
Classifier: Operating System :: Microsoft :: Windows :: Windows 10
Classifier: Operating System :: POSIX :: Linux
Classifier: Operating System :: MacOS :: MacOS X
Classifier: Programming Language :: C++
Classifier: Programming Language :: Python :: 3
Classifier: Programming Language :: Python :: 3 :: Only
Classifier: Programming Language :: Python :: 3.8
Classifier: Programming Language :: Python :: 3.9
Classifier: Programming Language :: Python :: 3.10
Classifier: Programming Language :: Python :: 3.11
Classifier: Programming Language :: Python :: 3.12
Requires-Python: >=3.8
License-File: COPYING
Requires-Dist: numpy
Provides-Extra: plotting
Requires-Dist: matplotlib>=2.2.0; extra == "plotting"
Provides-Extra: vis
Requires-Dist: pyglet>=1.5.27; extra == "vis"
Requires-Dist: vispy>=0.12.1; extra == "vis"
